vortexcrypt/__init__.py
vortexcrypt/cli.py
vortexcrypt/engine.py
vortexcrypt/io.py
vortexcrypt-1.0.7.dist-info/entry_points.txt
vortexcrypt-1.0.7.dist-info/LICENSE
vortexcrypt-1.0.7.dist-info/METADATA
vortexcrypt-1.0.7.dist-info/WHEEL
vortexcrypt-1.0.7.dist-info/RECORD
