Metadata-Version: 2.3
Name: vortexcrypt
Version: 1.0.7
Summary: A novel image encryption package based on time-reversible reaction-diffusion systems.
License: MIT
Keywords: encryption,image processing,reaction-diffusion,cryptography,Gray-Scott
Author: Fructueux Hollo
Author-email: fructueuxhollo@gmail.com>, Charbel Mamlankou <charbelzeusmamlankou@gmail.com>, Jude Agbodoyetin <judeseruch@gmail.com>, Ozias Deguenon <deguenonamen@gmail.com>, Marcellin Ogoungbe <ogoungbemarcellin@yahoo.com
Requires-Python: >=3.11
Classifier: License :: OSI Approved :: MIT License
Classifier: Programming Language :: Python :: 3
Classifier: Programming Language :: Python :: 3.11
Classifier: Programming Language :: Python :: 3.12
Classifier: Programming Language :: Python :: 3.13
Requires-Dist: numba (>=0.61.2,<0.62.0)
Requires-Dist: numpy (>=1.24,<2.3)
Requires-Dist: pillow (>=11.3.0,<12.0.0)
Requires-Dist: scipy (>=1.16.0,<2.0.0)
Requires-Dist: tqdm (>=4.67.1,<5.0.0)
Requires-Dist: typer[all] (>=0.16.0,<0.17.0)
Project-URL: Homepage, https://github.com/FructueuxHollo/vortexcrypt
Project-URL: Repository, https://github.com/FructueuxHollo/vortexcrypt
